passagemath_brial/__init__.py
passagemath_brial.libs/libbrial-83985df5.so.3.0.7
passagemath_brial.libs/libbrial_groebner-ccb100f5.so.3.0.7
passagemath_brial.libs/libgcc_s-2d945d6c.so.1
passagemath_brial.libs/libm4ri-18f60ecd.so.1.0.1
passagemath_brial.libs/libpng16-09496a15.so.16.43.0
passagemath_brial.libs/libstdc++-85f2cd6d.so.6.0.33
sage/all__sagemath_brial.py
sage/libs/all__sagemath_brial.py
sage/libs/polybori/__init__.pxd
sage/libs/polybori/decl.pxd
sage/libs/polybori/pb_wrap.h
sage/rings/all__sagemath_brial.py
sage/rings/polynomial/all__sagemath_brial.py
sage/rings/polynomial/pbori/PyPolyBoRi.py
sage/rings/polynomial/pbori/__init__.py
sage/rings/polynomial/pbori/blocks.py
sage/rings/polynomial/pbori/cnf.py
sage/rings/polynomial/pbori/easy_polynomials.py
sage/rings/polynomial/pbori/fglm.py
sage/rings/polynomial/pbori/frontend.py
sage/rings/polynomial/pbori/gbcore.py
sage/rings/polynomial/pbori/gbrefs.py
sage/rings/polynomial/pbori/heuristics.py
sage/rings/polynomial/pbori/interpolate.py
sage/rings/polynomial/pbori/interred.py
sage/rings/polynomial/pbori/ll.py
sage/rings/polynomial/pbori/nf.py
sage/rings/polynomial/pbori/parallel.py
sage/rings/polynomial/pbori/pbori.cpython-313-aarch64-linux-musl.so
sage/rings/polynomial/pbori/pbori.pxd
sage/rings/polynomial/pbori/pbori.pyx
sage/rings/polynomial/pbori/randompoly.py
sage/rings/polynomial/pbori/rank.py
sage/rings/polynomial/pbori/specialsets.py
sage/rings/polynomial/pbori/statistics.py
passagemath_brial-10.6.43.dist-info/METADATA
passagemath_brial-10.6.43.dist-info/WHEEL
passagemath_brial-10.6.43.dist-info/top_level.txt
passagemath_brial-10.6.43.dist-info/RECORD
